himpunan_discrete_sets_afl2-0.1.1.dist-info/licenses/LICENSE
set_function/__init__.py
set_function/__main__.py
set_function/cli.py
set_function/set_function.py
set_function/utils.py
himpunan_discrete_sets_afl2-0.1.1.dist-info/METADATA
himpunan_discrete_sets_afl2-0.1.1.dist-info/WHEEL
himpunan_discrete_sets_afl2-0.1.1.dist-info/entry_points.txt
himpunan_discrete_sets_afl2-0.1.1.dist-info/top_level.txt
himpunan_discrete_sets_afl2-0.1.1.dist-info/RECORD
