Metadata-Version: 2.4
Name: himpunan-discrete-sets-afl2
Version: 0.1.1
Summary: A package for set operations including union, intersection, difference, and symmetric difference.
Author-email: Group6 Discrete <letsworkwithinno@gmail.com>
Maintainer-email: Group6 Discrete <letsworkwithinno@gmail.com>
License: MIT
Project-URL: repository, https://github.com/1nnocentia/group6_afl2_setfunc.git
Project-URL: bugs, https://github.com/1nnocentia/group6_afl2_setfunc/issues
Project-URL: changelog, https://github.com/1nnocentia/group6_afl2_setfunc/blob/main/HISTORY.md
Project-URL: homepage, https://github.com/1nnocentia/group6_afl2_setfunc
Project-URL: documentation, https://github.com/1nnocentia/group6_afl2_setfunc/blob/main/README.md
Classifier: Development Status :: 4 - Beta
Classifier: Intended Audience :: Developers
Classifier: Intended Audience :: Education
Classifier: Intended Audience :: Science/Research
Classifier: License :: OSI Approved :: MIT License
Classifier: Natural Language :: English
Classifier: Programming Language :: Python :: 3
Classifier: Programming Language :: Python :: 3.10
Classifier: Programming Language :: Python :: 3.11
Classifier: Programming Language :: Python :: 3.12
Classifier: Programming Language :: Python :: 3.13
Classifier: Topic :: Scientific/Engineering :: Mathematics
Classifier: Topic :: Software Development :: Libraries :: Python Modules
Classifier: Topic :: Education
Requires-Python: >=3.10
License-File: LICENSE
Requires-Dist: typer
Provides-Extra: test
Requires-Dist: coverage>=7.0; extra == "test"
Requires-Dist: pytest>=7.0; extra == "test"
Requires-Dist: pytest-cov>=4.0; extra == "test"
Requires-Dist: ruff>=0.1.0; extra == "test"
Requires-Dist: mypy>=1.0; extra == "test"
Requires-Dist: ipdb>=0.13; extra == "test"
Provides-Extra: dev
Requires-Dist: build>=0.10; extra == "dev"
Requires-Dist: twine>=4.0; extra == "dev"
Requires-Dist: sphinx>=5.0; extra == "dev"
Requires-Dist: sphinx-rtd-theme>=1.0; extra == "dev"
Dynamic: license-file
